odoo/addons/l10n_it_delivery_note_base/README.rst
odoo/addons/l10n_it_delivery_note_base/__init__.py
odoo/addons/l10n_it_delivery_note_base/__manifest__.py
odoo/addons/l10n_it_delivery_note_base/hooks.py
odoo/addons/l10n_it_delivery_note_base/data/delivery_note_data.xml
odoo/addons/l10n_it_delivery_note_base/i18n/it.po
odoo/addons/l10n_it_delivery_note_base/i18n/l10n_it_delivery_note_base.pot
odoo/addons/l10n_it_delivery_note_base/migrations/13.0.1.0.0/noupdate_changes.xml
odoo/addons/l10n_it_delivery_note_base/migrations/13.0.1.0.0/post-migration.py
odoo/addons/l10n_it_delivery_note_base/models/__init__.py
odoo/addons/l10n_it_delivery_note_base/models/res_company.py
odoo/addons/l10n_it_delivery_note_base/models/stock_delivery_note_type.py
odoo/addons/l10n_it_delivery_note_base/models/stock_picking_goods_appearance.py
odoo/addons/l10n_it_delivery_note_base/models/stock_picking_transport_condition.py
odoo/addons/l10n_it_delivery_note_base/models/stock_picking_transport_method.py
odoo/addons/l10n_it_delivery_note_base/models/stock_picking_transport_reason.py
odoo/addons/l10n_it_delivery_note_base/readme/CONTRIBUTORS.rst
odoo/addons/l10n_it_delivery_note_base/readme/DESCRIPTION.rst
odoo/addons/l10n_it_delivery_note_base/security/ir.model.access.csv
odoo/addons/l10n_it_delivery_note_base/security/ir_module_category.xml
odoo/addons/l10n_it_delivery_note_base/security/ir_rule.xml
odoo/addons/l10n_it_delivery_note_base/security/res_groups.xml
odoo/addons/l10n_it_delivery_note_base/security/res_users.xml
odoo/addons/l10n_it_delivery_note_base/static/description/icon.png
odoo/addons/l10n_it_delivery_note_base/static/description/index.html
odoo/addons/l10n_it_delivery_note_base/views/stock_delivery_note_type.xml
odoo/addons/l10n_it_delivery_note_base/views/stock_picking_goods_appearance.xml
odoo/addons/l10n_it_delivery_note_base/views/stock_picking_transport_condition.xml
odoo/addons/l10n_it_delivery_note_base/views/stock_picking_transport_method.xml
odoo14_addon_l10n_it_delivery_note_base-14.0.1.0.2.dist-info/METADATA
odoo14_addon_l10n_it_delivery_note_base-14.0.1.0.2.dist-info/WHEEL
odoo14_addon_l10n_it_delivery_note_base-14.0.1.0.2.dist-info/top_level.txt
odoo14_addon_l10n_it_delivery_note_base-14.0.1.0.2.dist-info/RECORD
